uno/__init__.py
uno/__main__.py
uno/_card.py
uno/_color.py
uno/_colors.py
uno/_core.py
uno/_game.py
uno/_init.py
uno/_mods.py
uno/_player.py
uno/lang.py
uno/main.py
uno/_network/__init__.py
uno/_network/client.py
uno/_network/other.py
uno/_network/server.py
uno/_network/shared.py
Uno_Game-1.1.0.dist-info/METADATA
Uno_Game-1.1.0.dist-info/WHEEL
Uno_Game-1.1.0.dist-info/top_level.txt
Uno_Game-1.1.0.dist-info/RECORD
