Metadata-Version: 2.1
Name: Uno-Game
Version: 1.1.0
Summary: A recreation of the Uno card game
Home-page: https://github.com/gaming32/uno
Author: Gaming32
Author-email: gaming32i64@gmail.com
License: License :: OSI Approved :: MIT License
Platform: UNKNOWN
